.gitignore
.readthedocs.yaml
CONTRIBUTING.md
LICENSE.md
MANIFEST.in
README.md
pyproject.toml
pytest.ini
requirements.txt
setup.cfg
setup.py
.github/workflows/README.md
.github/workflows/cicd.yml
docs/.gitignore
docs/Makefile
docs/README.md
docs/conf.py
docs/index.md
docs/images/abaco_overview.png
docs/images/logo/abaco_logo.png
docs/images/logo/abaco_logo.svg
docs/tutorial/.jupytext
docs/tutorial/demo-mgnify-mgys-1135.ipynb
docs/tutorial/demo-mgnify-mgys-1135.py
docs/tutorial/demo-mgnify-tomatoes.ipynb
docs/tutorial/demo-mgnify-tomatoes.py
docs/tutorial/tutorial-anaerobic-digestion.ipynb
docs/tutorial/tutorial-anaerobic-digestion.py
docs/tutorial/data/dataset_ad.csv
docs/tutorial/data/mgnify_MGYS00001135.h5ad
src/abaco/ABaCo.py
src/abaco/__init__.py
src/abaco/batch_correction.py
src/abaco/dataloader.py
src/abaco/metrics.py
src/abaco/plots.py
src/abaco/utils.py
src/abaco.egg-info/PKG-INFO
src/abaco.egg-info/SOURCES.txt
src/abaco.egg-info/dependency_links.txt
src/abaco.egg-info/requires.txt
src/abaco.egg-info/top_level.txt
tests/__init__.py
tests/test_utils.py