Metadata-Version: 2.4
Name: abaco
Version: 0.1.1
Summary: Batch Effect Correction framework for metagenomic data
Author: Edir Sebastián Vidal Castro, Angel L. P., Henry Webel, Atieh Gharib, Juliana Assis, Sebastián Ayala-Ruano
Author-email: Alberto Santos <albsad@dtu.dk>
License-Expression: MIT
Project-URL: Bug Tracker, https://github.com/Multiomics-Analytics-Group/abaco/issues
Project-URL: homepage, https://github.com/Multiomics-Analytics-Group/abaco
Project-URL: repository, https://github.com/Multiomics-Analytics-Group/abaco
Project-URL: documentation, https://mona-abaco.readthedocs.io
Classifier: Programming Language :: Python :: 3.11
Classifier: Programming Language :: Python :: 3.12
Classifier: Operating System :: OS Independent
Requires-Python: >=3.11
License-File: LICENSE.md
Requires-Dist: anndata
Requires-Dist: array-api-compat
Requires-Dist: asttokens
Requires-Dist: biom-format
Requires-Dist: certifi
Requires-Dist: charset-normalizer
Requires-Dist: click
Requires-Dist: clustergrammer2
Requires-Dist: combat
Requires-Dist: comm
Requires-Dist: contourpy
Requires-Dist: crc32c
Requires-Dist: cycler
Requires-Dist: decorator
Requires-Dist: donfig
Requires-Dist: executing
Requires-Dist: fastcluster
Requires-Dist: filelock
Requires-Dist: fonttools
Requires-Dist: fsspec
Requires-Dist: h5py
Requires-Dist: idna
Requires-Dist: inmoose
Requires-Dist: ipython
Requires-Dist: ipython_pygments_lexers
Requires-Dist: ipywidgets
Requires-Dist: jedi
Requires-Dist: Jinja2
Requires-Dist: joblib
Requires-Dist: jupyterlab_widgets
Requires-Dist: kiwisolver
Requires-Dist: legacy-api-wrap
Requires-Dist: MarkupSafe
Requires-Dist: matplotlib
Requires-Dist: matplotlib-inline
Requires-Dist: mpmath
Requires-Dist: narwhals
Requires-Dist: natsort
Requires-Dist: networkx
Requires-Dist: numcodecs
Requires-Dist: numpy
Requires-Dist: packaging
Requires-Dist: pandas
Requires-Dist: parso
Requires-Dist: patsy
Requires-Dist: pexpect
Requires-Dist: pillow
Requires-Dist: plotly
Requires-Dist: prompt_toolkit
Requires-Dist: ptyprocess
Requires-Dist: pure_eval
Requires-Dist: Pygments
Requires-Dist: pyparsing
Requires-Dist: python-dateutil
Requires-Dist: pytz
Requires-Dist: PyYAML
Requires-Dist: requests
Requires-Dist: scanpy
Requires-Dist: scikit-bio
Requires-Dist: scikit-learn
Requires-Dist: scipy
Requires-Dist: seaborn
Requires-Dist: six
Requires-Dist: stack-data
Requires-Dist: statsmodels
Requires-Dist: sympy
Requires-Dist: threadpoolctl
Requires-Dist: torch
Requires-Dist: tqdm
Requires-Dist: traitlets
Requires-Dist: typing_extensions
Requires-Dist: tzdata
Requires-Dist: urllib3
Requires-Dist: wcwidth
Requires-Dist: widgetsnbextension
Requires-Dist: zarr
Provides-Extra: docs
Requires-Dist: sphinx; extra == "docs"
Requires-Dist: sphinx-book-theme; extra == "docs"
Requires-Dist: myst-nb; extra == "docs"
Requires-Dist: ipywidgets; extra == "docs"
Requires-Dist: sphinx-new-tab-link!=0.2.2; extra == "docs"
Requires-Dist: jupytext; extra == "docs"
Requires-Dist: sphinx-copybutton; extra == "docs"
Requires-Dist: anndata; extra == "docs"
Provides-Extra: dev
Requires-Dist: black[jupyter]; extra == "dev"
Requires-Dist: ruff; extra == "dev"
Requires-Dist: pytest; extra == "dev"
Requires-Dist: ipykernel; extra == "dev"
Dynamic: license-file
